tablarray/__init__.py
tablarray/interpolate.py
tablarray/misc.py
tablarray/mmul.py
tablarray/re.py
tablarray/set.py
tablarray/solve.py
tablarray/stack.py
tablarray/ta.py
tablarray/taplot.py
tablarray/taprint.py
tablarray/tashape.py
tablarray/version.py
tablarray/views.py
tablarray/kwtools/__init__.py
tablarray/kwtools/kwargs_db.py
tablarray/kwtools/kwargs_scan.py
tablarray/tanumpy/__init__.py
tablarray/tanumpy/linalg.py
tablarray/tanumpy/misc.py
tablarray/tanumpy/new.py
tablarray/tanumpy/np_func.py
tablarray/tascipy/__init__.py
tablarray/tascipy/linalg.py
tablarray/tascipy/sp_fun.py
tablarray/wraps/__init__.py
tablarray/wraps/cbroadcast.py
tablarray/wraps/funcnd.py
tablarray/wraps/lin.py
tablarray/wraps/op12swap.py
tablarray/wraps/sets.py
tablarray-0.5.0.dist-info/LICENSE
tablarray-0.5.0.dist-info/METADATA
tablarray-0.5.0.dist-info/WHEEL
tablarray-0.5.0.dist-info/top_level.txt
tablarray-0.5.0.dist-info/RECORD
