Metadata-Version: 2.1
Name: tablarray
Version: 0.5.0
Summary: Extend broadcasting rules of numpy to abstract tabularshape of data from cellular shape
Home-page: https://github.com/chriscannon9001/tablarray
Author: Chris Cannon
Author-email: chris.cannon.9001@gmail.com
License: BSD
Requires-Python: >=3.2
License-File: LICENSE
Requires-Dist: attrs
Requires-Dist: matplotlib
Requires-Dist: numpy
Provides-Extra: tascipy
Requires-Dist: scipy ; extra == 'tascipy'
